example.svg
dipswitch_svg/__init__.py
dipswitch_svg-0.1.2.dist-info/licenses/LICENSE
dipswitch_svg-0.1.2.dist-info/METADATA
dipswitch_svg-0.1.2.dist-info/WHEEL
dipswitch_svg-0.1.2.dist-info/top_level.txt
dipswitch_svg-0.1.2.dist-info/RECORD
