Metadata-Version: 2.4
Name: dipswitch_svg
Version: 0.1.2
Summary: SVG generation for dipswitch documentation
Author-email: PenguMC <pengurobotics@gmail.com>
Maintainer-email: PenguMC <pengurobotics@gmail.com>
License-Expression: MIT
Project-URL: Source, https://codeberg.org/PenguMC/dipswitch_svg
Keywords: svg,dipswitch
Classifier: Development Status :: 4 - Beta
Classifier: Programming Language :: Python :: 3
Classifier: Topic :: Documentation
Requires-Python: >=3
License-File: LICENSE
Dynamic: license-file
